pnvm/__init__.py
pnvm/console.py
pnvm/main.py
pnvm/utils.py
pnvm/verification.py
pnvm/cli/__init__.py
pnvm/cli/install.py
pnvm/cli/list.py
pnvm/cli/remove.py
pnvm/cli/switch.py
pnvm/cli/which.py
pnvm-0.2.0.dist-info/licenses/COPYING
pnvm-0.2.0.dist-info/METADATA
pnvm-0.2.0.dist-info/WHEEL
pnvm-0.2.0.dist-info/entry_points.txt
pnvm-0.2.0.dist-info/top_level.txt
pnvm-0.2.0.dist-info/RECORD
