Metadata-Version: 2.4
Name: pnvm
Version: 0.2.0
Author-email: "Axel H. Karlsson" <git@axelkarlsson.mozmail.com>
License-Expression: GPL-3.0-or-later
Requires-Python: >=3.13.5
License-File: COPYING
Dynamic: license-file
